{
  "font": "inherit",
  "form_tab_message": "Message",
  "tab_message_font": "inherit",
  "tab_message_size": "inherit",
  "tab_message_style": "normal",
  "tab_message_weight": "inherit",
  "tab_message_align": "inherit",
  "tab_message_width": "inherit",
  "tab_message_line_height": "inherit",
  "form_tab_mission": "Confier une mission",
  "tab_mission_font": "inherit",
  "tab_mission_size": "inherit",
  "tab_mission_style": "normal",
  "tab_mission_weight": "inherit",
  "tab_mission_align": "inherit",
  "tab_mission_width": "inherit",
  "tab_mission_line_height": "inherit",
  "form_titre_message": "ENVOYER UN MESSAGE",
  "titre_message_font": "inherit",
  "titre_message_size": "inherit",
  "titre_message_style": "normal",
  "titre_message_weight": "inherit",
  "titre_message_align": "inherit",
  "titre_message_width": "inherit",
  "titre_message_line_height": "inherit",
  "form_titre_mission": "CONFIER UNE MISSION",
  "titre_mission_font": "inherit",
  "titre_mission_size": "inherit",
  "titre_mission_style": "normal",
  "titre_mission_weight": "inherit",
  "titre_mission_align": "inherit",
  "titre_mission_width": "inherit",
  "titre_mission_line_height": "inherit",
  "info_rdv_label": "PRENDRE RENDEZ-VOUS",
  "rdv_label_font": "inherit",
  "rdv_label_size": "inherit",
  "rdv_label_style": "normal",
  "rdv_label_weight": "inherit",
  "rdv_label_align": "inherit",
  "rdv_label_width": "inherit",
  "rdv_label_line_height": "inherit",
  "rdv_texte_font": "inherit",
  "rdv_texte_size": "sm",
  "rdv_texte_style": "normal",
  "rdv_texte_weight": "inherit",
  "rdv_texte_align": "inherit",
  "rdv_texte_width": "inherit",
  "rdv_texte_line_height": "inherit",
  "info_email_label": "EMAIL",
  "email_label_font": "inherit",
  "email_label_size": "inherit",
  "email_label_style": "normal",
  "email_label_weight": "inherit",
  "email_label_align": "inherit",
  "email_label_width": "inherit",
  "email_label_line_height": "inherit",
  "info_tel_label": "TÉLÉPHONE",
  "tel_label_font": "inherit",
  "tel_label_size": "inherit",
  "tel_label_style": "normal",
  "tel_label_weight": "inherit",
  "tel_label_align": "inherit",
  "tel_label_width": "inherit",
  "tel_label_line_height": "inherit",
  "adresse_label_font": "inherit",
  "adresse_label_size": "inherit",
  "adresse_label_style": "normal",
  "adresse_label_weight": "inherit",
  "adresse_label_align": "inherit",
  "adresse_label_width": "inherit",
  "adresse_label_line_height": "inherit",
  "info_bouton_label": "VISITER LE VILLAGE",
  "bouton_label_font": "inherit",
  "bouton_label_size": "inherit",
  "bouton_label_style": "normal",
  "bouton_label_weight": "inherit",
  "bouton_label_align": "inherit",
  "bouton_label_width": "inherit",
  "bouton_label_line_height": "inherit"
}
